Metadata-Version: 1.0
Name: pocoui
Version: 1.0.94
Summary: Poco cross-engine UI automated test framework.
Home-page: https://github.com/AirtestProject/Poco
Author: Netease Games
Author-email: rockywhisper@163.com, lxhustauto@gmail.com
License: Apache License 2.0
Keywords: poco,automation test,ui automation
Platform: UNKNOWN
